{"width":1024,"SubTexture":[{"width":43,"y":957,"height":40,"name":"hand_1","x":625},{"width":109,"y":313,"height":388,"name":"Sword","x":308},{"width":25,"y":703,"height":18,"name":"finger","x":349},{"width":40,"y":957,"height":59,"name":"part","x":583},{"width":49,"y":879,"height":78,"name":"hand","x":482},{"width":103,"y":313,"height":173,"name":"torso","x":529},{"width":40,"y":879,"height":76,"name":"leg","x":583},{"width":238,"y":734,"height":213,"name":"head","x":242},{"width":39,"y":703,"height":20,"name":"foot","x":308},{"width":305,"y":423,"height":309,"name":"helm","x":1},{"frameX":-65,"y":1,"frameY":-14,"frameWidth":397,"width":296,"frameHeight":453,"height":420,"name":"fx","x":1},{"width":48,"y":879,"height":78,"name":"hand_e","x":533},{"width":108,"y":313,"height":389,"name":"sword_e","x":419},{"width":239,"y":734,"height":213,"name":"face_e","x":1},{"width":104,"y":704,"height":173,"name":"torso_e","x":482},{"width":304,"y":1,"height":310,"name":"helm_e","x":299},{"width":39,"y":879,"height":76,"name":"leg_e","x":625}],"imagePath":"newkiddb_tex.png","name":"newkiddb","height":1024}